pandas_ext/__init__.py
pandas_ext/amazon_spectrum.py
pandas_ext/csv.py
pandas_ext/gdrive.py
pandas_ext/json.py
pandas_ext/parquet.py
pandas_ext/sfdc.py
pandas_ext/sql.py
pandas_ext/sqla_utils.py
pandas_ext/xml.py
pandas_ext/common/__init__.py
pandas_ext/common/utils.py
pandas_ext-0.4.10.dist-info/LICENSE
pandas_ext-0.4.10.dist-info/METADATA
pandas_ext-0.4.10.dist-info/WHEEL
pandas_ext-0.4.10.dist-info/top_level.txt
pandas_ext-0.4.10.dist-info/RECORD
