Metadata-Version: 2.1
Name: pandas-ext
Version: 0.4.10
Summary: Python Pandas extensions for pandas dataframes
Home-page: https://github.com/newsela/pandas_ext
Author: Rich Fernandez, Sean Massot, Brian Tenazas, Luke Orland
Author-email: devs@newsela.com
License: MIT
Platform: UNKNOWN
Classifier: Development Status :: 3 - Alpha
Classifier: Programming Language :: Python :: 3.6
Classifier: Programming Language :: Python :: 2.7
Requires-Dist: Jinja2 (>=2.10)
Requires-Dist: pandas (>=0.22)
Requires-Dist: pyarrow (>=0.11.1)
Requires-Dist: requests (>=2.20.0)
Requires-Dist: s3fs (>=0.1.5)
